singleton_injector/__init__.py
singleton_injector/injector.py
singleton_injector/singleton.py
singleton_injector-0.2.dist-info/LICENSE.txt
singleton_injector-0.2.dist-info/METADATA
singleton_injector-0.2.dist-info/WHEEL
singleton_injector-0.2.dist-info/top_level.txt
singleton_injector-0.2.dist-info/RECORD
