Metadata-Version: 2.1
Name: singleton-injector
Version: 0.2
Summary: Simple library to unify singleton and injection with a decorator
Home-page: https://github.com/santiagoMeloMedina/singleton-injector
Author: Santiago Melo Medina
Author-email: smelomedina05@gmail.com
License: MIT
Download-URL: https://github.com/santiagoMeloMedina/singleton-injector/archive/refs/tags/0.1.tar.gz
Keywords: Injection,Singleton,Simple
Platform: UNKNOWN
Classifier: Development Status :: 4 - Beta
Classifier: Intended Audience :: Developers
Classifier: Topic :: Software Development :: Build Tools
Classifier: License :: OSI Approved :: MIT License
Classifier: Programming Language :: Python :: 3.8
License-File: LICENSE.txt
